polymarket_apis/__init__.py
polymarket_apis/clients/__init__.py
polymarket_apis/clients/clob_client.py
polymarket_apis/clients/data_client.py
polymarket_apis/clients/gamma_client.py
polymarket_apis/clients/graphql_client.py
polymarket_apis/clients/web3_client.py
polymarket_apis/clients/websockets_client.py
polymarket_apis/types/__init__.py
polymarket_apis/types/clob_types.py
polymarket_apis/types/common.py
polymarket_apis/types/data_types.py
polymarket_apis/types/gamma_types.py
polymarket_apis/types/web3_types.py
polymarket_apis/types/websockets_types.py
polymarket_apis/utilities/__init__.py
polymarket_apis/utilities/config.py
polymarket_apis/utilities/constants.py
polymarket_apis/utilities/endpoints.py
polymarket_apis/utilities/exceptions.py
polymarket_apis/utilities/headers.py
polymarket_apis/utilities/order_builder/__init__.py
polymarket_apis/utilities/order_builder/builder.py
polymarket_apis/utilities/order_builder/helpers.py
polymarket_apis/utilities/signing/__init__.py
polymarket_apis/utilities/signing/eip712.py
polymarket_apis/utilities/signing/hmac.py
polymarket_apis/utilities/signing/model.py
polymarket_apis/utilities/signing/signer.py
polymarket_apis/utilities/web3/__init__.py
polymarket_apis/utilities/web3/helpers.py
polymarket_apis/utilities/web3/abis/CTFExchange.json
polymarket_apis/utilities/web3/abis/ConditionalTokens.json
polymarket_apis/utilities/web3/abis/NegRiskAdapter.json
polymarket_apis/utilities/web3/abis/NegRiskCtfExchange.json
polymarket_apis/utilities/web3/abis/ProxyWalletFactory.json
polymarket_apis/utilities/web3/abis/Safe.json
polymarket_apis/utilities/web3/abis/SafeProxyFactory.json
polymarket_apis/utilities/web3/abis/UChildERC20Proxy.json
polymarket_apis/utilities/web3/abis/__init__.py
polymarket_apis/utilities/web3/abis/custom_contract_errors.py
polymarket_apis-0.4.3.dist-info/METADATA
polymarket_apis-0.4.3.dist-info/WHEEL
polymarket_apis-0.4.3.dist-info/RECORD
