Metadata-Version: 2.4
Name: polymarket-apis
Version: 0.4.3
Summary: Unified Polymarket APIs with Pydantic data validation - Clob, Gamma, Data, Web3, Websockets, GraphQL clients.
Project-URL: repository, https://github.com/qualiaenjoyer/polymarket-apis
Author-email: Razvan Gheorghe <razvan@gheorghe.me>
Requires-Python: >=3.12
Requires-Dist: gql[httpx]>=4.0.0
Requires-Dist: httpx[http2]>=0.25.1
Requires-Dist: lomond>=0.3.3
Requires-Dist: poly-eip712-structs>=0.0.1
Requires-Dist: py-order-utils>=0.3.2
Requires-Dist: pydantic>=2.10.5
Requires-Dist: python-dateutil>=2.9.0
Requires-Dist: web3>=7.0
Requires-Dist: wsaccel>=0.6.7
